irsensors/__init__.py
irsensors/irsensor.py
irsensors/irsensorset.py
irsensors/__pycache__/__init__.cpython-37.pyc
irsensors/__pycache__/irsensor.cpython-37.pyc
irsensors/__pycache__/irsensorset.cpython-37.pyc
irsensors/basic_program/base.py
irsensors/serial/__init__.py
irsensors/serial/__init__.pyc
irsensors/serial/aio.py
irsensors/serial/aio.pyc
irsensors/serial/errors.py
irsensors/serial/hooks.py
irsensors/serial/marshal.py
irsensors/serial/meta.py
irsensors/serial/model.py
irsensors/serial/properties.py
irsensors/serial/request.py
irsensors/serial/rfc2217.py
irsensors/serial/rfc2217.pyc
irsensors/serial/rs485.py
irsensors/serial/rs485.pyc
irsensors/serial/serialcli.py
irsensors/serial/serialcli.pyc
irsensors/serial/serialjava.py
irsensors/serial/serialjava.pyc
irsensors/serial/serialposix.py
irsensors/serial/serialposix.pyc
irsensors/serial/serialutil.py
irsensors/serial/serialutil.pyc
irsensors/serial/serialwin32.py
irsensors/serial/serialwin32.pyc
irsensors/serial/test.py
irsensors/serial/win32.py
irsensors/serial/win32.pyc
irsensors/serial/__pycache__/__init__.cpython-37.pyc
irsensors/serial/__pycache__/aio.cpython-37.pyc
irsensors/serial/__pycache__/errors.cpython-37.pyc
irsensors/serial/__pycache__/hooks.cpython-37.pyc
irsensors/serial/__pycache__/marshal.cpython-37.pyc
irsensors/serial/__pycache__/meta.cpython-37.pyc
irsensors/serial/__pycache__/model.cpython-37.pyc
irsensors/serial/__pycache__/properties.cpython-37.pyc
irsensors/serial/__pycache__/request.cpython-37.pyc
irsensors/serial/__pycache__/rfc2217.cpython-37.pyc
irsensors/serial/__pycache__/rs485.cpython-37.pyc
irsensors/serial/__pycache__/serialcli.cpython-37.pyc
irsensors/serial/__pycache__/serialjava.cpython-37.pyc
irsensors/serial/__pycache__/serialposix.cpython-37.pyc
irsensors/serial/__pycache__/serialutil.cpython-37.pyc
irsensors/serial/__pycache__/serialwin32.cpython-37.pyc
irsensors/serial/__pycache__/test.cpython-37.pyc
irsensors/serial/__pycache__/win32.cpython-37.pyc
irsensors-0.0.8.dist-info/METADATA
irsensors-0.0.8.dist-info/WHEEL
irsensors-0.0.8.dist-info/top_level.txt
irsensors-0.0.8.dist-info/RECORD
