Metadata-Version: 2.1
Name: irsensors
Version: 0.0.8
Summary: This package allows to read data from an IR sensor set connected by USB.
Home-page: https://github.com/Gillou100/educat_irsensor/tree/master/irsensors
Author: Gilles HUBERT
Author-email: gilles.hubert@isen.yncrea.fr
License: UNKNOWN
Requires-Dist: pyserial
